pifm/__init__.py
pifm/array.py
pifm/astpp.py
pifm/node_rules.py
pifm/pifm_errors.py
pifm/template_ast_validator.py
pifm/usage_ast_validator.py
pifm-0.0.1.dist-info/METADATA
pifm-0.0.1.dist-info/WHEEL
pifm-0.0.1.dist-info/top_level.txt
pifm-0.0.1.dist-info/RECORD
