Metadata-Version: 2.1
Name: pifm
Version: 0.0.1
Summary: Python In-Formal Methods Library
Author: Tom Kunc
Classifier: Programming Language :: Python :: 3
Classifier: Operating System :: OS Independent
Requires-Python: >=3.6
